{"anime_post":[{"username":"nish","title":"Naruto","type":"action","seasons":"25","episodes":"10","rank":"9"},{"username":"nish","title":"Death Note","type":"action","seasons":"1","episodes":"24","rank":"10"},{"username":"arrey","title":"asdf","type":"action","seasons":"5","episodes":"3","rank":"6"},{"username":"nish","title":"boroto","type":"action","seasons":"5","episodes":"3","rank":"6"},{"username":"the goon","title":"haikuu","type":"comedy","seasons":"4","episodes":"10","rank":"4"},{"username":"new user","title":"hunter x hunter","type":"action","seasons":"5","episodes":"10","rank":"7"},{"username":"yooo","title":"hunter x hunter","type":"comedy","seasons":"10","episodes":"4","rank":"0"}]}